{
  "SignUp": [
    {
      "name": "MAHA",
      "email": "emahe1208@gmail.com",
      "password": "Maha1208",
      "phone": "9876543212",
      "id": 1
    }
  ],
  "AddressPayment": [
    {
      "fullname": "maha",
      "email": "maha@gmail.com",
      "address": "karpaga",
      "city": "chennai",
      "state": "Tamilnadu",
      "zipcode": "600119",
      "id": 1
    },
    {
      "name": "b",
      "email": "maha@gmail.com",
      "address": "m",
      "city": "m",
      "state": "k",
      "zipcode": "9u",
      "id": 2
    }
  ]
}